neuroquery/VERSION.txt
neuroquery/__init__.py
neuroquery/_compat.py
neuroquery/datasets.py
neuroquery/encoding.py
neuroquery/img_utils.py
neuroquery/nmf.py
neuroquery/ridge.py
neuroquery/smoothed_regression.py
neuroquery/tokenization.py
neuroquery/data/highlight.xsl
neuroquery/data/nltk_stop_words.txt
neuroquery-1.1.0.dist-info/METADATA
neuroquery-1.1.0.dist-info/WHEEL
neuroquery-1.1.0.dist-info/licenses/LICENSE
neuroquery-1.1.0.dist-info/RECORD
