Metadata-Version: 2.4
Name: neuroquery
Version: 1.1.0
Summary: Meta-analysis of neuroimaging studies.
Project-URL: Source code, https://github.com/neuroquery/neuroquery
Author-email: Jérôme Dockès <jerome@dockes.org>
License-File: LICENSE
Keywords: meta-analysis,neuroimaging
Classifier: Intended Audience :: Science/Research
Classifier: License :: OSI Approved :: BSD License
Classifier: Operating System :: OS Independent
Classifier: Programming Language :: Python :: 3
Classifier: Topic :: Scientific/Engineering
Classifier: Topic :: Software Development :: Libraries
Requires-Python: >=3.10
Requires-Dist: joblib>=1.1.1
Requires-Dist: lxml
Requires-Dist: nilearn>=0.9.2
Requires-Dist: numpy>=1.23.5
Requires-Dist: pandas>=1.5.3
Requires-Dist: regex
Requires-Dist: requests
Requires-Dist: scikit-learn>=1.2.1
Requires-Dist: scipy>=1.9.3
Provides-Extra: dev
Requires-Dist: coverage; extra == 'dev'
Requires-Dist: nltk>=3.4.5; extra == 'dev'
Requires-Dist: pytest; extra == 'dev'
Requires-Dist: pytest-cov; extra == 'dev'
Provides-Extra: stemming
Requires-Dist: nltk>=3.4.5; extra == 'stemming'
